PHASEfilter/__init__.py
PHASEfilter/bin/__init__.py
PHASEfilter/bin/copy_raw_data_example_phasefilter.py
PHASEfilter/bin/install_phasefilter_dependencies.sh
PHASEfilter/bin/make_alignment.py
PHASEfilter/bin/phasefilter.py
PHASEfilter/bin/phasefilter_single.py
PHASEfilter/bin/reference_statistics.py
PHASEfilter/bin/synchronize_genomes.py
PHASEfilter/lib/__init__.py
PHASEfilter/lib/constants/__init__.py
PHASEfilter/lib/constants/constants.py
PHASEfilter/lib/constants/version.py
PHASEfilter/lib/process/__init__.py
PHASEfilter/lib/process/process_genomes.py
PHASEfilter/lib/process/process_references.py
PHASEfilter/lib/utils/__init__.py
PHASEfilter/lib/utils/blast_two_sequences.py
PHASEfilter/lib/utils/chain.py
PHASEfilter/lib/utils/lastz_two_sequences.py
PHASEfilter/lib/utils/lift_over_simple.py
PHASEfilter/lib/utils/read_gff.py
PHASEfilter/lib/utils/reference.py
PHASEfilter/lib/utils/run_extra_software.py
PHASEfilter/lib/utils/software.py
PHASEfilter/lib/utils/testing_software.py
PHASEfilter/lib/utils/util.py
PHASEfilter/lib/utils/vcf_process.py
PHASEfilter/tests/__init__.py
PHASEfilter/tests/test_chain.py
PHASEfilter/tests/test_lift_over.py
PHASEfilter/tests/test_process_genomes.py
PHASEfilter/tests/test_reference.py
PHASEfilter/tests/test_run_extra_software.py
PHASEfilter/tests/test_software.py
PHASEfilter/tests/test_synchronization.py
PHASEfilter/tests/test_utils.py
PHASEfilter/tests/test_vcf.py
PHASEfilter/tests/files/__init__.py
PHASEfilter/tests/files/gff3/file_result_test_gff.gff3
PHASEfilter/tests/files/gff3/file_result_translate_gff.gff3
PHASEfilter/tests/files/gff3/to_translate.gff
PHASEfilter/tests/files/real_raw_data/Assembly22_hapA_To_Assembly22_hapB.over.chain
PHASEfilter/tests/files/real_raw_data/Assembly22_hapB_To_Assembly22_hapA.over.chain
PHASEfilter/tests/files/real_raw_data/Ca22chr7A_C_albicans_SC5314.fasta
PHASEfilter/tests/files/real_raw_data/Ca22chr7B_C_albicans_SC5314.fasta
PHASEfilter/tests/files/real_raw_data/T1_Fluc_7A_indels.vcf.gz
PHASEfilter-1.1.0.dist-info/LICENSE
PHASEfilter-1.1.0.dist-info/METADATA
PHASEfilter-1.1.0.dist-info/WHEEL
PHASEfilter-1.1.0.dist-info/entry_points.txt
PHASEfilter-1.1.0.dist-info/top_level.txt
PHASEfilter-1.1.0.dist-info/RECORD
